nershcalculator/__init__.py
nershcalculator/nershcalculator.py
nershcalculator-0.3.1.dist-info/WHEEL
nershcalculator-0.3.1.dist-info/METADATA
nershcalculator-0.3.1.dist-info/RECORD
