Metadata-Version: 2.1
Name: nershcalculator
Version: 0.3.1
Summary: Calculator module
Author-email: Nerijus Sakinis <nerijus.sakinis@gmail.com>
Classifier: License :: OSI Approved :: MIT License
Project-URL: Home, https://github.com/NerijusSh/calculator
